cob/__init__.py
cob/app.py
cob/app_utils.py
cob/bootstrapping.py
cob/ctx.py
cob/defs.py
cob/exceptions.py
cob/locations.py
cob/project.py
cob/pytest_plugin.py
cob/service_manager.py
cob/_skeletons/grain-blueprint
cob/_skeletons/grain-models
cob/_skeletons/grain-tasks
cob/_skeletons/grain-views
cob/_skeletons/grain-bundle/.cob.yml
cob/_skeletons/grain-frontend-ember/.cob.yml
cob/_skeletons/grain-static/.cob.yml
cob/_skeletons/grain-static/root/.cob.git.keep
cob/_skeletons/grain-templates/.cob.yml
cob/_skeletons/project/.cob-project.yml
cob/_skeletons/project/.dockerignore
cob/_skeletons/project/.gitignore
cob/_skeletons/static_dir/.cob.yml
cob/celery/__init__.py
cob/celery/app.py
cob/celery/utils.py
cob/cli/__init__.py
cob/cli/celery_cli.py
cob/cli/db_cli.py
cob/cli/develop_cli.py
cob/cli/docker_cli.py
cob/cli/exceptions.py
cob/cli/generate_cli.py
cob/cli/info_cli.py
cob/cli/list_cli.py
cob/cli/main.py
cob/cli/migrate_cli.py
cob/cli/testserver_cli.py
cob/cli/utils.py
cob/subsystems/__init__.py
cob/subsystems/base.py
cob/subsystems/flask_blueprint_subsystem.py
cob/subsystems/frontend.py
cob/subsystems/manager.py
cob/subsystems/models_subsystem.py
cob/subsystems/static_subsystem.py
cob/subsystems/tasks_subsystem.py
cob/subsystems/templates_subsystem.py
cob/subsystems/unittests.py
cob/subsystems/views_subsystem.py
cob/templates/Dockerfile.j2
cob/templates/nginx_config.j2
cob/templates/systemd_unit.j2
cob/utils/__init__.py
cob/utils/config.py
cob/utils/develop.py
cob/utils/docker.py
cob/utils/network.py
cob/utils/parsing.py
cob/utils/python.py
cob/utils/templates.py
cob/utils/unittests.py
cob/utils/url.py
cob-0.24.1.data/data/cob/_skeletons/grain-blueprint
cob-0.24.1.data/data/cob/_skeletons/grain-models
cob-0.24.1.data/data/cob/_skeletons/grain-tasks
cob-0.24.1.data/data/cob/_skeletons/grain-views
cob-0.24.1.data/data/cob/_skeletons/grain-bundle/.cob.yml
cob-0.24.1.data/data/cob/_skeletons/grain-frontend-ember/.cob.yml
cob-0.24.1.dist-info/AUTHORS
cob-0.24.1.dist-info/LICENSE
cob-0.24.1.dist-info/METADATA
cob-0.24.1.dist-info/WHEEL
cob-0.24.1.dist-info/entry_points.txt
cob-0.24.1.dist-info/pbr.json
cob-0.24.1.dist-info/top_level.txt
cob-0.24.1.dist-info/RECORD
