Metadata-Version: 2.1
Name: cob
Version: 0.24.1
Summary: Cob is a powerful framework for building full-stack web applications
Home-page: https://cob.readthedocs.org
Author: Rotem Yaari
Author-email: vmalloc@gmail.com
License: BSD3
Platform: UNKNOWN
Classifier: Development Status :: 4 - Beta
Classifier: Environment :: Console
Classifier: Intended Audience :: Developers
Classifier: Operating System :: OS Independent
Classifier: Programming Language :: Python
Requires-Dist: tmuxp (<2,>=1.5.0)
Requires-Dist: celery (<4.2.0)
Requires-Dist: click (<8,>=7.0)
Requires-Dist: emport (>=1.2.0)
Requires-Dist: gossip
Requires-Dist: Flask
Requires-Dist: Flask-Migrate
Requires-Dist: Flask-SQLAlchemy
Requires-Dist: Flask-Loopback
Requires-Dist: Jinja2
Requires-Dist: gunicorn
Requires-Dist: IPython
Requires-Dist: Logbook
Requires-Dist: mitba
Requires-Dist: psycopg2
Requires-Dist: PyYAML (>5.1)
Requires-Dist: pytest
Requires-Dist: redis
Requires-Dist: sentinels
Requires-Dist: virtualenv
Requires-Dist: yaspin
